{
    "last_account": 1,
    "num": 2,
    "account": [
        {
            "access_key": "v2_qb4caGtYfK2CYXI4hhtTkXSH3GKCDHY-S5qYWW1Y99F_VpSjBROSSSL5cRPZBSI91TNsMlxdUG36oc4i_cMj_tbNRXQ57g==.CAE=",
            "uid": "275689449",
            "name": "一语悠长",
            "type": "官服",
            "note": "21414905",
            "mid": "0tcme3i096_mhy"
        },
        {
            "access_key": "v2_SRZJCyinMN8UjTFKpI0ynmJBEZV_zZAhnpJINELAFz-S7nK7jymCeX5wPym8JJOET9XJG-YA2Ij94ywy5JSCzW0xgfEahCLz8fqlL9Eps4M0F1O4nbvBTmLnt3DLk5bPVhdbUtAf5H4c82A=.CAE=",
            "uid": "159606351",
            "name": "法芙娜v",
            "type": "官服",
            "note": "",
            "mid": "0tx7d39ifp_mhy"
        }
    ],
    "default_account_uid": "275689449",
    "default_account_server_type": 1
}